README.rst
setup.py
predix/__init__.py
predix/app.py
predix/config.py
predix/service.py
predix.egg-info/PKG-INFO
predix.egg-info/SOURCES.txt
predix.egg-info/dependency_links.txt
predix.egg-info/entry_points.txt
predix.egg-info/requires.txt
predix.egg-info/top_level.txt
predix/admin/__init__.py
predix/admin/acs.py
predix/admin/analytics.py
predix/admin/app.py
predix/admin/asset.py
predix/admin/blobstore.py
predix/admin/cache.py
predix/admin/config.py
predix/admin/dbaas.py
predix/admin/eventhub.py
predix/admin/logstash.py
predix/admin/service.py
predix/admin/timeseries.py
predix/admin/uaa.py
predix/admin/weather.py
predix/admin/cf/__init__.py
predix/admin/cf/api.py
predix/admin/cf/apps.py
predix/admin/cf/config.py
predix/admin/cf/orgs.py
predix/admin/cf/services.py
predix/admin/cf/spaces.py
predix/admin/ie/__init__.py
predix/admin/ie/parking.py
predix/data/__init__.py
predix/data/asset.py
predix/data/blobstore.py
predix/data/cache.py
predix/data/dbaas.py
predix/data/timeseries.py
predix/data/weather.py
predix/data/eventhub/EventHub_pb2.py
predix/data/eventhub/EventHub_pb2_grpc.py
predix/data/eventhub/Health_pb2.py
predix/data/eventhub/Health_pb2_grpc.py
predix/data/eventhub/__init__.py
predix/data/eventhub/client.py
predix/data/eventhub/publisher.py
predix/data/eventhub/subscriber.py
predix/ie/__init__.py
predix/ie/parking.py
predix/security/__init__.py
predix/security/acs.py
predix/security/uaa.py