Metadata-Version: 1.1
Name: predix
Version: 1.0.0
Summary: Python Client SDK for Predix Services
Home-page: https://github.com/PredixDev/predixpy
Author: Jayson DeLancey
Author-email: jayson.delancey@ge.com
License: UNKNOWN
Keywords: predix,ge,asset,analytics
Platform: UNKNOWN
Classifier: Intended Audience :: Developers
Classifier: Natural Language :: English
Classifier: Programming Language :: Python :: 2.7
Classifier: Programming Language :: Python :: 3.6
Classifier: License :: OSI Approved :: BSD License
Classifier: Development Status :: 3 - Alpha
